mixed_chromedriver/__init__.py
mixed_chromedriver/driver.py
mixed_chromedriver/selector.py
mixed_chromedriver-0.3.dist-info/METADATA
mixed_chromedriver-0.3.dist-info/WHEEL
mixed_chromedriver-0.3.dist-info/top_level.txt
mixed_chromedriver-0.3.dist-info/RECORD
