Metadata-Version: 2.1
Name: mixed-chromedriver
Version: 0.3
Summary: mixed_chromedriver is a flexible Chrome driver wrapper that extends Selenium, Selenium Wire, and Undetected Chromedriver, offering handy automation methods and an easy-to-use Selector for element selection.
Home-page: https://github.com/tranngocminhhieu/mixed-chromedriver
Author: Tran Ngoc Minh Hieu
Author-email: tnmhieu@gmail.com
Requires-Dist: selenium
Requires-Dist: selenium-wire
Requires-Dist: undetected-chromedriver
